tetra_hub/__init__.py
tetra_hub/_cli.py
tetra_hub/_version.py
tetra_hub/api_status_codes.py
tetra_hub/client.py
tetra_hub/hub.py
tetra_hub/public_api_pb2.py
tetra_hub/public_api_pb2.pyi
tetra_hub/public_rest_api.py
tetra_hub/py.typed
tetra_hub/test/__init__.py
tetra_hub/test/test_cli.py
tetra_hub/test/test_client.py
tetra_hub/test/test_public_rest_api.py
tetra_hub/test/test_zipped_model.py
tetra_hub/util/__init__.py
tetra_hub/util/dataset_entries_converters.py
tetra_hub/util/session.py
tetra_hub/util/zipped_model.py
tetra_hub-0.7.0.dist-info/METADATA
tetra_hub-0.7.0.dist-info/WHEEL
tetra_hub-0.7.0.dist-info/entry_points.txt
tetra_hub-0.7.0.dist-info/top_level.txt
tetra_hub-0.7.0.dist-info/RECORD
