Metadata-Version: 2.1
Name: tetra-hub
Version: 0.7.0
Summary: Python API for Tetra Hub.
Home-page: https://tetra.ai/
Author: Tetra Intelligence Systems Inc.
Author-email: support@tetra.ai
License: BSD License
Platform: UNKNOWN
Classifier: Development Status :: 2 - Pre-Alpha
Classifier: Intended Audience :: Developers
Classifier: Operating System :: MacOS :: MacOS X
Classifier: Operating System :: POSIX :: Linux
Classifier: Operating System :: Microsoft :: Windows
Classifier: Programming Language :: Python :: 3.7
Classifier: Programming Language :: Python :: 3.8
Classifier: Programming Language :: Python :: 3.9
Classifier: Programming Language :: Python :: 3.10
Classifier: Programming Language :: Python :: 3.11
Classifier: Topic :: Scientific/Engineering
Classifier: Topic :: Software Development
Requires-Python: >=3.7
Requires-Dist: requests
Requires-Dist: deprecation
Requires-Dist: packaging >=20.0
Requires-Dist: requests-toolbelt
Requires-Dist: tqdm
Requires-Dist: protobuf <4,>=3.15
Requires-Dist: numpy <2,>=1.22.0
Requires-Dist: h5py <4,>=3.6.0
Requires-Dist: prettytable >=3.9.0
Provides-Extra: coremltools
Requires-Dist: coremltools ==6.2 ; extra == 'coremltools'
Provides-Extra: onnx
Requires-Dist: onnx ==1.13.1 ; extra == 'onnx'
Provides-Extra: torch
Requires-Dist: torch ==2.0.1 ; extra == 'torch'
Requires-Dist: torchvision ==0.15.2 ; extra == 'torch'
